{
  "locked": false,
  "players": [
    {
      "id": "p1779936707998",
      "name": "Tessa"
    },
    {
      "id": "p1779936725338",
      "name": "Mark"
    },
    {
      "id": "p1779936796017",
      "name": "Mildred"
    },
    {
      "id": "p1779936803050",
      "name": "Emily"
    },
    {
      "id": "p1779936810074",
      "name": "Bryce"
    },
    {
      "id": "p1779936817378",
      "name": "Liz"
    },
    {
      "id": "p1779936822308",
      "name": "Alissa"
    },
    {
      "id": "p1779936827805",
      "name": "Sam"
    }
  ],
  "draftOrder": [
    "p1779936707998",
    "p1779936725338",
    "p1779936796017",
    "p1779936803050",
    "p1779936810074",
    "p1779936817378",
    "p1779936822308",
    "p1779936827805"
  ],
  "ownership": {
    "Spain": "p1779936707998",
    "France": "p1779936725338",
    "England": "p1779936796017",
    "Brazil": "p1779936803050",
    "Portugal": "p1779936810074",
    "Argentina": "p1779936817378",
    "Netherlands": "p1779936822308",
    "Belgium": "p1779936827805",
    "Switzerland": "p1779936707998",
    "Croatia": "p1779936725338",
    "Norway": "p1779936796017",
    "Colombia": "p1779936803050",
    "Senegal": "p1779936810074",
    "Mexico": "p1779936817378",
    "Morocco": "p1779936822308",
    "Germany": "p1779936827805"
  },
  "draftComplete": false,
  "draftIndex": 16
}